rctiplus_rabbitmq_python_sdk/__init__.py
rctiplus_rabbitmq_python_sdk/aio_rabbitmq.py
rctiplus_rabbitmq_python_sdk/message_payload.py
rctiplus_rabbitmq_python_sdk/rabbitmq.py
tests/__init__.py
tests/aio_get_queues.py
tests/aio_receive.py
tests/aio_send.py
tests/receive.py
tests/send.py
rctiplus_rabbitmq_python_sdk-1.2.1.dist-info/LICENSE
rctiplus_rabbitmq_python_sdk-1.2.1.dist-info/METADATA
rctiplus_rabbitmq_python_sdk-1.2.1.dist-info/WHEEL
rctiplus_rabbitmq_python_sdk-1.2.1.dist-info/top_level.txt
rctiplus_rabbitmq_python_sdk-1.2.1.dist-info/RECORD
