Metadata-Version: 2.1
Name: rctiplus-rabbitmq-python-sdk
Version: 1.2.1
Summary: A library from RCTI+ to handle RabbitMQ tasks (connect, send, receive, etc) in Python.
Home-page: UNKNOWN
Author: RCTI+
Author-email: rctiplus.webmaster@gmail.com
License: GPLv3
Keywords: python,rabbitmq,rctiplus,rcti+,sdk
Platform: UNKNOWN
Classifier: Programming Language :: Python :: 3
Classifier: License :: OSI Approved :: GNU General Public License v3 or later (GPLv3+)
Classifier: Operating System :: OS Independent
Requires-Python: >=3.7.3
Requires-Dist: pika (==1.2.0)
Requires-Dist: aio-pika (==6.8.0)
Requires-Dist: requests (==2.25.1)
